Workbook

Sheet Assumptions
A1: DemandMap — Financial Model | B1: $10K Budget | $10K Profit Target | 6 Months
A3: PRICING ASSUMPTIONS
A4: Free tier price | B4: 0 | C4: Unlimited free tier to drive signups
A5: Starter tier price ($/mo) | B5: 29 | C5: 1 city, 3 users, all features
A6: Pro tier price ($/mo) | B6: 79 | C6: 3 cities, 10 users, API access
A7: Avg revenue per paying user ($/mo) | B7: 35 | C7: Blended: mostly Starter + some Pro
A8: Free-to-paid conversion rate | B8: 0.14 | C8: Industry avg 5-10%; we target 12% with street demos
A9: Monthly churn rate (paying) | B9: 0.05 | C9: Food trucks are seasonal; expect higher early churn
A11: SIGNUP ASSUMPTIONS (per month)
B12: 25 | C12: 40 | D12: 45 | E12: 40 | F12: 30 | G12: 25 | H12: 6-Mo Total
A13: New signups from street team | B13: 25 | C13: 40 | D13: 45 | E13: 40 | F13: 30 | G13: 25 | H13: =SUM(B13:G13) -> 205
A14: New signups from paid ads | B14: 8 | C14: 20 | D14: 35 | E14: 50 | F14: 65 | G14: 80 | H14: =SUM(B14:G14) -> 258
A15: New signups from referrals | B15: 0 | C15: 5 | D15: 12 | E15: 22 | F15: 35 | G15: 45 | H15: =SUM(B15:G15) -> 119
A16: Total new signups | B16: =B13+B14+B15 -> 33 | C16: =C13+C14+C15 -> 65 | D16: =D13+D14+D15 -> 92 | E16: =E13+E14+E15 -> 112 | F16: =F13+F14+F15 -> 130 | G16: =G13+G14+G15 -> 150 | H16: =SUM(B16:G16) -> 582
A18: COST ASSUMPTIONS (per month)
B19: Month 1 | C19: Month 2 | D19: Month 3 | E19: Month 4 | F19: Month 5 | G19: Month 6 | H19: 6-Mo Total
A20: Person 1 — hrs/week | B20: 8 | C20: 10 | D20: 10 | E20: 8 | F20: 6 | G20: 5
A21: Person 2 — hrs/week | B21: 0 | C21: 6 | D21: 8 | E21: 8 | F21: 6 | G21: 5
A22: Hourly rate ($) | B22: 20 | C22: 10 | D22: 10 | E22: 8 | F22: 6 | G22: 5
A23: Weeks per month | B23: 4.3 | C23: 6 | D23: 8 | E23: 8 | F23: 6 | G23: 5
A24: Street team monthly cost | B24: =(B20+B21)*$B$22*$B$23 -> 688 | C24: =(C20+C21)*$B$22*$B$23 -> 1376 | D24: =(D20+D21)*$B$22*$B$23 -> 1548 | E24: =(E20+E21)*$B$22*$B$23 -> 1376 | F24: =(F20+F21)*$B$22*$B$23 -> 1032 | G24: =(G20+G21)*$B$22*$B$23 -> 860 | H24: =SUM(B24:G24) -> 6880
A25: Paid ad spend | B25: 100 | C25: 200 | D25: 300 | E25: 400 | F25: 500 | G25: 500 | H25: =SUM(B25:G25) -> 2000
A26: Materials (stickers, cards, tees) | B26: 300 | C26: 0 | D26: 50 | E26: 0 | F26: 0 | G26: 0 | H26: =SUM(B26:G26) -> 350
A27: Tools (Canva, domain, tripod) | B27: 47 | C27: 13 | D27: 13 | E27: 13 | F27: 13 | G27: 13 | H27: =SUM(B27:G27) -> 112
A28: Stripe processing fee rate | B28: 0.029 | C28: 200 | D28: 300 | E28: 400 | F28: 500 | G28: 500
B29: 300 | C29: 0 | D29: 50 | E29: 0 | F29: 0 | G29: 0
B30: 47 | C30: 13 | D30: 13 | E30: 13 | F30: 13 | G30: 13

Sheet P&L
A1: Profit & Loss — 6-Month Projection
B3: Month 1 | C3: Month 2 | D3: Month 3 | E3: Month 4 | F3: Month 5 | G3: Month 6 | H3: 6-Mo Total
A4: USERS
A5: New signups | B5: =Assumptions!B16 -> 33 | C5: =Assumptions!C16 -> 65 | D5: =Assumptions!D16 -> 92 | E5: =Assumptions!E16 -> 112 | F5: =Assumptions!F16 -> 130 | G5: =Assumptions!G16 -> 150 | H5: =SUM(B5:G5) -> 582
A6: Cumulative free users | B6: =B5 -> 33 | C6: =B6+C5 -> 98 | D6: =C6+D5 -> 190 | E6: =D6+E5 -> 302 | F6: =E6+F5 -> 432 | G6: =F6+G5 -> 582 | H6: =G6 -> 582
A7: New conversions to paid | B7: =ROUND(B6*Assumptions!$B$8,0) -> 5 | C7: =ROUND(C6*Assumptions!$B$8,0) -> 14 | D7: =ROUND(D6*Assumptions!$B$8,0) -> 27 | E7: =ROUND(E6*Assumptions!$B$8,0) -> 42 | F7: =ROUND(F6*Assumptions!$B$8,0) -> 60 | G7: =ROUND(G6*Assumptions!$B$8,0) -> 81 | H7: =SUM(B7:G7) -> 229
A8: Churned paying users | B8: 0 | C8: =ROUND(B9*Assumptions!$B$9,0) -> 0 | D8: =ROUND(C9*Assumptions!$B$9,0) -> 1 | E8: =ROUND(D9*Assumptions!$B$9,0) -> 2 | F8: =ROUND(E9*Assumptions!$B$9,0) -> 4 | G8: =ROUND(F9*Assumptions!$B$9,0) -> 7 | H8: =SUM(B8:G8) -> 14
A9: Active paying users (end of month) | B9: =B7-B8 -> 5 | C9: =B9+C7-C8 -> 19 | D9: =C9+D7-D8 -> 45 | E9: =D9+E7-E8 -> 85 | F9: =E9+F7-F8 -> 141 | G9: =F9+G7-G8 -> 215 | H9: =G9 -> 215
A11: REVENUE
A12: Subscription revenue | B12: =B9*Assumptions!$B$7 -> 175 | C12: =C9*Assumptions!$B$7 -> 665 | D12: =D9*Assumptions!$B$7 -> 1575 | E12: =E9*Assumptions!$B$7 -> 2975 | F12: =F9*Assumptions!$B$7 -> 4935 | G12: =G9*Assumptions!$B$7 -> 7525 | H12: =SUM(B12:G12) -> 17850
A13: Less: payment processing (3.5%) | B13: =-B12*0.035 -> -6.125 | C13: =-C12*0.035 -> -23.275 | D13: =-D12*0.035 -> -55.125 | E13: =-E12*0.035 -> -104.125 | F13: =-F12*0.035 -> -172.725 | G13: =-G12*0.035 -> -263.375
A14: Net Revenue | B14: =B12+B13 -> 168.875 | C14: =C12+C13 -> 641.725 | D14: =D12+D13 -> 1519.875 | E14: =E12+E13 -> 2870.875 | F14: =F12+F13 -> 4762.275 | G14: =G12+G13 -> 7261.625 | H14: =SUM(B14:G14) -> 17225.25
A16: COSTS
A17: Street team ($20/hr) | B17: =Assumptions!B24 -> 688 | C17: =Assumptions!C24 -> 1376 | D17: =Assumptions!D24 -> 1548 | E17: =Assumptions!E24 -> 1376 | F17: =Assumptions!F24 -> 1032 | G17: =Assumptions!G24 -> 860 | H17: =SUM(B17:G17) -> 6880
A18: Paid ads (Meta + Google + TikTok) | B18: =Assumptions!B25 -> 100 | C18: =Assumptions!C25 -> 200 | D18: =Assumptions!D25 -> 300 | E18: =Assumptions!E25 -> 400 | F18: =Assumptions!F25 -> 500 | G18: =Assumptions!G25 -> 500 | H18: =SUM(B18:G18) -> 2000
A19: Materials + swag | B19: =Assumptions!B26 -> 300 | C19: =Assumptions!C26 -> 0 | D19: =Assumptions!D26 -> 50 | E19: =Assumptions!E26 -> 0 | F19: =Assumptions!F26 -> 0 | G19: =Assumptions!G26 -> 0 | H19: =SUM(B19:G19) -> 350
A20: Tools + subscriptions | B20: =Assumptions!B27 -> 47 | C20: =Assumptions!C27 -> 13 | D20: =Assumptions!D27 -> 13 | E20: =Assumptions!E27 -> 13 | F20: =Assumptions!F27 -> 13 | G20: =Assumptions!G27 -> 13 | H20: =SUM(B20:G20) -> 112
A21: Total Costs | B21: =B17+B18+B19+B20 -> 1135 | C21: =C17+C18+C19+C20 -> 1589 | D21: =D17+D18+D19+D20 -> 1911 | E21: =E17+E18+E19+E20 -> 1789 | F21: =F17+F18+F19+F20 -> 1545 | G21: =G17+G18+G19+G20 -> 1373 | H21: =SUM(B21:G21) -> 9342
A23: BOTTOM LINE
A24: Monthly Profit / (Loss) | B24: =B14-B21 -> -966.125 | C24: =C14-C21 -> -947.275 | D24: =D14-D21 -> -391.125 | E24: =E14-E21 -> 1081.875 | F24: =F14-F21 -> 3217.275 | G24: =G14-G21 -> 5888.625 | H24: =SUM(B24:G24) -> 7883.25
A25: Cumulative Profit / (Loss) | B25: =B24 -> -966.125 | C25: =B25+C24 -> -1913.4 | D25: =C25+D24 -> -2304.525 | E25: =D25+E24 -> -1222.65 | F25: =E25+F24 -> 1994.625 | G25: =F25+G24 -> 7883.25 | H25: =G25 -> 7883.25
A27: KEY METRICS
A28: MRR (Monthly Recurring Revenue) | B28: =B12 -> 175 | C28: =C12 -> 665 | D28: =D12 -> 1575 | E28: =E12 -> 2975 | F28: =F12 -> 4935 | G28: =G12 -> 7525
A29: CAC — Street (cost per signup) | B29: =IFERROR(B17/Assumptions!B13,0) -> 27.52 | C29: =IFERROR(C17/Assumptions!C13,0) -> 34.4 | D29: =IFERROR(D17/Assumptions!D13,0) -> 34.4 | E29: =IFERROR(E17/Assumptions!E13,0) -> 34.4 | F29: =IFERROR(F17/Assumptions!F13,0) -> 34.4 | G29: =IFERROR(G17/Assumptions!G13,0) -> 34.4
A30: CAC — Ads (cost per signup) | B30: =IFERROR(B18/Assumptions!B14,0) -> 12.5 | C30: =IFERROR(C18/Assumptions!C14,0) -> 10 | D30: =IFERROR(D18/Assumptions!D14,0) -> 8.5714286 | E30: =IFERROR(E18/Assumptions!E14,0) -> 8 | F30: =IFERROR(F18/Assumptions!F14,0) -> 7.6923077 | G30: =IFERROR(G18/Assumptions!G14,0) -> 6.25
A31: LTV (ARPU / monthly churn) | B31: =Assumptions!$B$7/Assumptions!$B$9 -> 700
A32: LTV:CAC ratio (blended) | B32: =IFERROR(B31/(((B17+B18)/(Assumptions!B13+Assumptions!B14))),0) -> 29.314721 | C32: =IFERROR(C31/(((C17+C18)/(Assumptions!C13+Assumptions!C14))),0) -> 0 | D32: =IFERROR(D31/(((D17+D18)/(Assumptions!D13+Assumptions!D14))),0) -> 0 | E32: =IFERROR(E31/(((E17+E18)/(Assumptions!E13+Assumptions!E14))),0) -> 0 | F32: =IFERROR(F31/(((F17+F18)/(Assumptions!F13+Assumptions!F14))),0) -> 0 | G32: =IFERROR(G31/(((G17+G18)/(Assumptions!G13+Assumptions!G14))),0) -> 0
A33: Monthly burn rate | B33: =B21 -> 1135 | C33: =C21 -> 1589 | D33: =D21 -> 1911 | E33: =E21 -> 1789 | F33: =F21 -> 1545 | G33: =G21 -> 1373

Sheet Scenarios
A1: Scenario Analysis — Path to $10K Profit
B3: Conservative | C3: Base Case | D3: Aggressive
A4: 6-mo signups (total) | B4: 350 | C4: 580 | D4: 850
A5: Free-to-paid conversion | B5: 0.1 | C5: 0.14 | D5: 0.2
A6: Avg revenue/user/mo | B6: 29 | C6: 35 | D6: 42
A7: Monthly churn | B7: 0.07 | C7: 0.05 | D7: 0.03
A9: Paying users at month 6 | B9: =ROUND(B4*B5,0) -> 35 | C9: =ROUND(C4*C5,0) -> 81 | D9: =ROUND(D4*D5,0) -> 170
A10: MRR at month 6 | B10: =B9*B6 -> 1015 | C10: =C9*C6 -> 2835 | D10: =D9*D6 -> 7140
A11: 6-mo total revenue (est) | B11: =B10*3.5 -> 3552.5 | C11: =C10*3.5 -> 9922.5 | D11: =D10*3.5 -> 24990
A13: Total 6-mo costs | B13: 9342 | C13: 9342 | D13: 9342
A15: 6-Month Profit / (Loss) | B15: =B11-B13 -> -5789.5 | C15: =C11-C13 -> 580.5 | D15: =D11-D13 -> 15648
A16: Months to $10K cumulative profit | B16: =IFERROR(ROUND((10000+B13)/(B10*0.965),1),"N/A") -> 19.7 | C16: =IFERROR(ROUND((10000+C13)/(C10*0.965),1),"N/A") -> 7.1 | D16: =IFERROR(ROUND((10000+D13)/(D10*0.965),1),"N/A") -> 2.8
A19: Total costs are $9,342 over 6 months. Revenue must reach $19,342 to net $10K profit.
A20: At $35 ARPU, that means ~553 paying user-months (e.g., ~92 avg paying users over 6 months).
A21: Base case P&L model projects $7,883 profit. Aggressive case exceeds $10K.
A22: Key lever: conversion rate. Moving from 14% to 20% nearly doubles the paying base.
A23: Secondary lever: churn. Dropping from 5% to 3% adds ~30 paying users by month 6.
A24: At $20/hr, each street marketer costs ~$1K/mo. Scale hours down as ads take over.
A25: Secondary lever: churn. Dropping from 6% to 4% adds ~15 paying users by month 6.

Sheet Ad Budget
A1: Paid Ad Budget Breakdown
B3: Month 1 | C3: Month 2 | D3: Month 3 | E3: Month 4 | F3: Month 5 | G3: Month 6 | H3: 6-Mo Total
A4: META (Instagram + Facebook)
A5: Spend | B5: 50 | C5: 100 | D5: 175 | E5: 250 | F5: 325 | G5: 325 | H5: =SUM(B5:G5) -> 1225
A6: CPM ($) | B6: 5 | C6: 4.5 | D6: 4 | E6: 3.5 | F6: 3.5 | G6: 3.5
A7: Impressions | B7: =ROUND(B5/B6*1000,0) -> 10000 | C7: =ROUND(C5/C6*1000,0) -> 22222 | D7: =ROUND(D5/D6*1000,0) -> 43750 | E7: =ROUND(E5/E6*1000,0) -> 71429 | F7: =ROUND(F5/F6*1000,0) -> 92857 | G7: =ROUND(G5/G6*1000,0) -> 92857 | H7: =SUM(B7:G7) -> 333115
A8: CTR | B8: 0.015 | C8: 0.018 | D8: 0.02 | E8: 0.022 | F8: 0.025 | G8: 0.025
A9: Clicks | B9: =ROUND(B7*B8,0) -> 150 | C9: =ROUND(C7*C8,0) -> 400 | D9: =ROUND(D7*D8,0) -> 875 | E9: =ROUND(E7*E8,0) -> 1571 | F9: =ROUND(F7*F8,0) -> 2321 | G9: =ROUND(G7*G8,0) -> 2321 | H9: =SUM(B9:G9) -> 7638
A10: Signup conversion rate | B10: 0.08 | C10: 0.1 | D10: 0.12 | E10: 0.13 | F10: 0.14 | G10: 0.15
A11: Signups from Meta | B11: =ROUND(B9*B10,0) -> 12 | C11: =ROUND(C9*C10,0) -> 40 | D11: =ROUND(D9*D10,0) -> 105 | E11: =ROUND(E9*E10,0) -> 204 | F11: =ROUND(F9*F10,0) -> 325 | G11: =ROUND(G9*G10,0) -> 348 | H11: =SUM(B11:G11) -> 1034
A12: Cost per signup (Meta) | B12: =IFERROR(B5/B11,0) -> 4.1666667 | C12: =IFERROR(C5/C11,0) -> 2.5 | D12: =IFERROR(D5/D11,0) -> 1.6666667 | E12: =IFERROR(E5/E11,0) -> 1.2254902 | F12: =IFERROR(F5/F11,0) -> 1 | G12: =IFERROR(G5/G11,0) -> 0.93390805
A14: GOOGLE SEARCH ADS
A15: Spend | B15: 50 | C15: 125 | D15: 150 | E15: 175 | F15: 175 | G15: 175 | H15: =SUM(B15:G15) -> 850
A16: Avg CPC ($) | B16: 2 | C16: 1.8 | D16: 1.5 | E16: 1.5 | F16: 1.4 | G16: 1.4
A17: Clicks | B17: 35 | C17: 70 | D17: 85 | E17: 100 | F17: 115 | G17: 115 | H17: =SUM(B17:G17) -> 520
A18: Signup conversion rate | B18: 0.12 | C18: 0.14 | D18: 0.16 | E18: 0.17 | F18: 0.18 | G18: 0.18
A19: Signups from Google | B19: =ROUND(B17*B18,0) -> 4 | C19: =ROUND(C17*C18,0) -> 10 | D19: =ROUND(D17*D18,0) -> 14 | E19: =ROUND(E17*E18,0) -> 17 | F19: =ROUND(F17*F18,0) -> 21 | G19: =ROUND(G17*G18,0) -> 21 | H19: =SUM(B19:G19) -> 87
A20: Cost per signup (Google) | B20: =IFERROR(B15/B19,0) -> 12.5 | C20: =IFERROR(C15/C19,0) -> 12.5 | D20: =IFERROR(D15/D19,0) -> 10.714286 | E20: =IFERROR(E15/E19,0) -> 10.294118 | F20: =IFERROR(F15/F19,0) -> 8.3333333 | G20: =IFERROR(G15/G19,0) -> 8.3333333
A22: TIKTOK SPARK ADS
A23: Spend | B23: 25 | C23: 50 | D23: 75 | E23: 75 | F23: 75 | G23: 75 | H23: =SUM(B23:G23) -> 375
A24: CPM ($) | B24: 3 | C24: 2.5 | D24: 2.5 | E24: 2 | F24: 2 | G24: 2
A25: Impressions | B25: =ROUND(B23/B24*1000,0) -> 8333 | C25: =ROUND(C23/C24*1000,0) -> 20000 | D25: =ROUND(D23/D24*1000,0) -> 30000 | E25: =ROUND(E23/E24*1000,0) -> 37500 | F25: =ROUND(F23/F24*1000,0) -> 37500 | G25: =ROUND(G23/G24*1000,0) -> 37500 | H25: =SUM(B25:G25) -> 170833
A26: CTR | B26: 0.01 | C26: 0.015 | D26: 0.02 | E26: 0.02 | F26: 0.025 | G26: 0.025
A27: Clicks | B27: =ROUND(B25*B26,0) -> 83 | C27: =ROUND(C25*C26,0) -> 300 | D27: =ROUND(D25*D26,0) -> 600 | E27: =ROUND(E25*E26,0) -> 750 | F27: =ROUND(F25*F26,0) -> 938 | G27: =ROUND(G25*G26,0) -> 938 | H27: =SUM(B27:G27) -> 3609
A28: Signup conversion rate | B28: 0.06 | C28: 0.08 | D28: 0.1 | E28: 0.1 | F28: 0.12 | G28: 0.12
A29: Signups from TikTok | B29: =ROUND(B27*B28,0) -> 5 | C29: =ROUND(C27*C28,0) -> 24 | D29: =ROUND(D27*D28,0) -> 60 | E29: =ROUND(E27*E28,0) -> 75 | F29: =ROUND(F27*F28,0) -> 113 | G29: =ROUND(G27*G28,0) -> 113 | H29: =SUM(B29:G29) -> 390
A30: Cost per signup (TikTok) | B30: 15 | C30: 30 | D30: 40 | E30: 50 | F30: 60 | G30: 60
A32: TOTAL AD PERFORMANCE
A33: Total ad spend | B33: =B5+B15+B23 -> 125 | C33: =C5+C15+C23 -> 275 | D33: =D5+D15+D23 -> 400 | E33: =E5+E15+E23 -> 500 | F33: =F5+F15+F23 -> 575 | G33: =G5+G15+G23 -> 575 | H33: =SUM(B33:G33) -> 2450
A34: Total signups from ads | B34: =B11+B19+B29 -> 21 | C34: =C11+C19+C29 -> 74 | D34: =D11+D19+D29 -> 179 | E34: =E11+E19+E29 -> 296 | F34: =F11+F19+F29 -> 459 | G34: =G11+G19+G29 -> 482 | H34: =SUM(B34:G34) -> 1511
A35: Blended cost per signup | B35: =IFERROR(B33/B34,0) -> 5.952381 | C35: =IFERROR(C33/C34,0) -> 3.7162162 | D35: =IFERROR(D33/D34,0) -> 2.2346369 | E35: =IFERROR(E33/E34,0) -> 1.6891892 | F35: =IFERROR(F33/F34,0) -> 1.2527233 | G35: =IFERROR(G33/G34,0) -> 1.1929461 | H35: =IFERROR(H33/H34,0) -> 1.6214428
